README.rst
setup.py
fluentd_log_handler/__init__.py
fluentd_log_handler/handler.py
fluentd_log_handler.egg-info/PKG-INFO
fluentd_log_handler.egg-info/SOURCES.txt
fluentd_log_handler.egg-info/dependency_links.txt
fluentd_log_handler.egg-info/requires.txt
fluentd_log_handler.egg-info/top_level.txt