Metadata-Version: 1.1
Name: fluentd-log-handler
Version: 0.0.7
Summary: Python logging handler for Fluentd
Home-page: https://github.com/neillab/fluentdloghandler
Author: Hyun-Tae Hwang
Author-email: hwanght1@gmail.com
License: GPL
Platform: UNKNOWN
Classifier: Development Status :: 3 - Alpha
Classifier: Programming Language :: Python :: 3
Classifier: Topic :: System :: Logging
Classifier: Intended Audience :: Developers
